dendritecli/__init__.py
dendritecli/_sql.py
dendritecli/_version.py
dendritecli/api.py
dendritecli/main.py
dendritecli-1.2.0.post1.dist-info/licenses/LICENSE
tests/__init__.py
tests/_mock_server.py
tests/test_api.py
dendritecli-1.2.0.post1.dist-info/METADATA
dendritecli-1.2.0.post1.dist-info/WHEEL
dendritecli-1.2.0.post1.dist-info/entry_points.txt
dendritecli-1.2.0.post1.dist-info/top_level.txt
dendritecli-1.2.0.post1.dist-info/RECORD
