Metadata-Version: 2.4
Name: dendritecli
Version: 1.2.0.post1
Summary: Manage the Dendrite API from your command line!
Author-email: Nexus <pip@nexy7574.co.uk>
License:                     GNU GENERAL PUBLIC LICENSE
Project-URL: Source, https://github.com/nexy7574/dendritecli
Project-URL: Chat, https://matrix.to/#/#ontopic:nexy74574.co.uk
Project-URL: Funding, https://ko-fi.com/nexy7574
Requires-Python: >=3.10
License-File: LICENSE
Requires-Dist: click<9,>=8.1.7
Requires-Dist: rich<14,>=13.6.0
Requires-Dist: httpx[brotli,http2]>=0.25.0
Requires-Dist: toml>=0.10.2
Requires-Dist: psycopg<4,>=3.1.12
Provides-Extra: dev
Requires-Dist: pytest>=7.4.3; extra == "dev"
Requires-Dist: fastapi>=0.104.1; extra == "dev"
Requires-Dist: pytest-dependency>=0.5.1; extra == "dev"
Requires-Dist: ruff~=0.4; extra == "dev"
Dynamic: license-file
